CustomPresentationBuilder.py
__init__.py
pptx_builder-0.1.0.dist-info/METADATA
pptx_builder-0.1.0.dist-info/WHEEL
pptx_builder-0.1.0.dist-info/top_level.txt
pptx_builder-0.1.0.dist-info/RECORD
