Metadata-Version: 2.1
Name: pptx-builder
Version: 0.1.0
Summary: Simplify the creation of PowerPoint presentations with pandas DataFrames and multi-image arrangements.
Requires-Python: >=3.12
Requires-Dist: python-pptx>=1.0.2
